attributecode/__init__.py
attributecode/__main__.py
attributecode/api.py
attributecode/attrib.py
attributecode/attrib_util.py
attributecode/cmd.py
attributecode/gen.py
attributecode/licenses.py
attributecode/model.py
attributecode/transform.py
attributecode/util.py
attributecode/templates/default_html.template
attributecode/templates/default_json.template
attributecode/templates/license_ref.template
attributecode/templates/list.csv
attributecode/templates/scancode_html.template
aboutcode_toolkit-11.0.0.dist-info/AUTHORS.rst
aboutcode_toolkit-11.0.0.dist-info/CHANGELOG.rst
aboutcode_toolkit-11.0.0.dist-info/CODE_OF_CONDUCT.rst
aboutcode_toolkit-11.0.0.dist-info/METADATA
aboutcode_toolkit-11.0.0.dist-info/NOTICE
aboutcode_toolkit-11.0.0.dist-info/WHEEL
aboutcode_toolkit-11.0.0.dist-info/apache-2.0.LICENSE
aboutcode_toolkit-11.0.0.dist-info/entry_points.txt
aboutcode_toolkit-11.0.0.dist-info/top_level.txt
aboutcode_toolkit-11.0.0.dist-info/RECORD
