Metadata-Version: 2.1
Name: aboutcode-toolkit
Version: 11.0.0
Summary: AboutCode-toolkit is a tool to document the provenance (origin and license) of third-party software using small text files. Collect inventories and generate attribution documentation.
Home-page: https://github.com/nexB/aboutcode-toolkit
Author: nexB. Inc. and others
Author-email: info@aboutcode.org
License: Apache-2.0
Keywords: license,about,metadata,package,copyright,attribution,software,inventory,open source,sca,SBOM,spdx
Classifier: Development Status :: 5 - Production/Stable
Classifier: Intended Audience :: Developers
Classifier: Programming Language :: Python :: 3 :: Only
Classifier: Programming Language :: Python :: 3.7
Classifier: Programming Language :: Python :: 3.8
Classifier: Programming Language :: Python :: 3.9
Classifier: Programming Language :: Python :: 3.10
Classifier: Topic :: Software Development
Classifier: Topic :: Software Development :: Documentation
Classifier: Topic :: Software Development :: Quality Assurance
Classifier: Topic :: System :: Software Distribution
Classifier: Topic :: Utilities
Requires-Python: >=3.7
License-File: apache-2.0.LICENSE
License-File: NOTICE
License-File: AUTHORS.rst
License-File: CHANGELOG.rst
License-File: CODE_OF_CONDUCT.rst
Requires-Dist: attrs
Requires-Dist: boolean.py >=3.5
Requires-Dist: certifi
Requires-Dist: click
Requires-Dist: jinja2
Requires-Dist: license-expression >=0.94
Requires-Dist: openpyxl
Requires-Dist: packageurl-python >=0.9.0
Requires-Dist: saneyaml
Provides-Extra: docs
Requires-Dist: Sphinx >=5.0.2 ; extra == 'docs'
Requires-Dist: sphinx-rtd-theme >=1.0.0 ; extra == 'docs'
Requires-Dist: sphinx-reredirects >=0.1.2 ; extra == 'docs'
Requires-Dist: doc8 >=0.11.2 ; extra == 'docs'
Provides-Extra: testing
Requires-Dist: pytest !=7.0.0,>=6 ; extra == 'testing'
Requires-Dist: pytest-xdist >=2 ; extra == 'testing'
Requires-Dist: twine ; extra == 'testing'
Requires-Dist: black ; extra == 'testing'
Requires-Dist: isort ; extra == 'testing'
